[
  {
    "name": "Squelette — vue antérieure",
    "category": "Système Musculosquelettique",
    "image": "schemas/squelette_vue_anterieure.jpg",
    "elements": [
      { "number": 1, "answer": "Crâne" },
      { "number": 2, "answer": "Clavicule" },
      { "number": 3, "answer": "Sternum" },
      { "number": 4, "answer": "Côtes" },
      { "number": 5, "answer": "Humérus" },
      { "number": 6, "answer": "Radius" },
      { "number": 7, "answer": "Ulna (cubitus)" },
      { "number": 8, "answer": "Pelvis" },
      { "number": 9, "answer": "Os carpiens" },
      { "number": 10, "answer": "Os métacarpiens" },
      { "number": 11, "answer": "Phalanges" },
      { "number": 12, "answer": "Fémur" },
      { "number": 13, "answer": "Patella (rotule)" },
      { "number": 14, "answer": "Tibia" },
      { "number": 15, "answer": "Fibula (péroné)" },
      { "number": 16, "answer": "Os tarsiens" },
      { "number": 17, "answer": "Os métatarsiens" },
      { "number": 18, "answer": "Phalanges" }
    ]
  },
  {
    "name": "Squelette — vue latérale",
    "category": "Système Musculosquelettique",
    "image": "schemas/squelette_vue_laterale.jpg",
    "elements": [
      { "number": 1, "answer": "Crâne" },
      { "number": 2, "answer": "Vertèbres cervicales" },
      { "number": 3, "answer": "Scapula (omoplate)" },
      { "number": 4, "answer": "Côtes" },
      { "number": 5, "answer": "Vertèbres thoraciques" },
      { "number": 6, "answer": "Vertèbre lombale" },
      { "number": 7, "answer": "Pelvis" },
      { "number": 8, "answer": "Sacrum" },
      { "number": 9, "answer": "Coccyx" },
      { "number": 10, "answer": "Fémur" },
      { "number": 11, "answer": "Patella (rotule)" },
      { "number": 12, "answer": "Tibia" },
      { "number": 13, "answer": "Fibula (péroné)" },
      { "number": 14, "answer": "Os tarsiens" },
      { "number": 15, "answer": "Calcanéus" },
      { "number": 16, "answer": "Os métatarsiens" },
      { "number": 17, "answer": "Phalanges" }
    ]
  }
]
